LICENSE.txt
MANIFEST.in
NOTICE.txt
Ontap.py
README.txt
setup.cfg
setup.py
examples/backup-vmware-netapp/backup-vmware-netapp.py
examples/backup-vmware-netapp/vmware-netapp-backup-auth.yaml
examples/backup-vmware-netapp/vmware-netapp-backup-config.yaml
examples/netapp-force-autosize/README.txt
examples/netapp-force-autosize/netapp-force-autosize.py
examples/netapp-force-autosize/netapp-space-check.yaml
netapp/DfmErrno.py
netapp/NaElement.py
netapp/NaErrno.py
netapp/NaServer.py
netapp/NaServer.py.orig
netapp/README.txt
netapp/__init__.py
netapp/optional_ssl_verification.patch
ontap_api_wrapper.egg-info/PKG-INFO
ontap_api_wrapper.egg-info/SOURCES.txt
ontap_api_wrapper.egg-info/dependency_links.txt
ontap_api_wrapper.egg-info/requires.txt
ontap_api_wrapper.egg-info/top_level.txt