Metadata-Version: 1.1
Name: ontap-api-wrapper
Version: 0.5.4.post0
Summary: Python wrapper for NetApp Manageability SDK
Home-page: https://github.com/machalekj/ontap-api-wrapper
Author: Jiri Machalek
Author-email: machalekj@gmail.com
License: Apache License
Download-URL: https://github.com/machalekj/ontap-api-wrapper/archive/v0.5.4.tar.gz
Platform: UNKNOWN
Classifier: Intended Audience :: Developers
Classifier: License :: OSI Approved :: Apache Software License
Classifier: Topic :: Software Development :: Libraries :: Python Modules
Classifier: Programming Language :: Python :: 2.7
Classifier: Programming Language :: Python :: 3
Classifier: Programming Language :: Python :: 3.4
Classifier: Programming Language :: Python :: 3.5
Classifier: Programming Language :: Python :: 3.6
